tests/__init__.py
tests/test_enum.py
venum/__init__.py
venum/core.py
venum-1.1.0.dist-info/DESCRIPTION.rst
venum-1.1.0.dist-info/METADATA
venum-1.1.0.dist-info/RECORD
venum-1.1.0.dist-info/WHEEL
venum-1.1.0.dist-info/metadata.json
venum-1.1.0.dist-info/top_level.txt
