Metadata-Version: 2.0
Name: venum
Version: 1.1.0
Summary: Verifiably better, validated Enum
Home-page: https://github.com/ofek/venum
Author: Ofek Lev
Author-email: ofekmeister@gmail.com
License: MIT
Download-URL: https://github.com/ofek/venum
Keywords: enum,immutable,functional,data structures
Platform: UNKNOWN
Classifier: Development Status :: 5 - Production/Stable
Classifier: Intended Audience :: Developers
Classifier: License :: OSI Approved :: MIT License
Classifier: Natural Language :: English
Classifier: Operating System :: OS Independent
Classifier: Programming Language :: Python :: 2.7
Classifier: Programming Language :: Python :: 3.3
Classifier: Programming Language :: Python :: 3.4
Classifier: Programming Language :: Python :: 3.5
Classifier: Programming Language :: Python :: 3.6
Classifier: Programming Language :: Python :: Implementation :: CPython
Classifier: Programming Language :: Python :: Implementation :: PyPy
